libmake/__init__.py
libmake/makefile.py
libmake/version.py
libmake/watch.py
libmake/elements/__init__.py
libmake/elements/prerequisite.py
libmake/elements/recipe.py
libmake/elements/rule.py
libmake/elements/target.py
libmake/globals/__init__.py
libmake/globals/alias.py
libmake/globals/make_vars.py
libmake/globals/rule_vars.py
libmake/utils/__init__.py
libmake/utils/file.py
lmcli/__init__.py
libmake-0.3.1.dist-info/METADATA
libmake-0.3.1.dist-info/WHEEL
libmake-0.3.1.dist-info/entry_points.txt
libmake-0.3.1.dist-info/top_level.txt
libmake-0.3.1.dist-info/RECORD
