Metadata-Version: 2.1
Name: libmake
Version: 0.3.1
Summary: Building blocks for make-like utils
Home-page: https://github.com/AleCandido/libmake.py
Author: A.Candido
Author-email: candido.ale@gmail.com
License: UNKNOWN
Platform: UNKNOWN
Classifier: Programming Language :: Python
Classifier: Programming Language :: Python :: 3
Requires-Python: >=3.7
Requires-Dist: anytree
Requires-Dist: rich
